CHANGELOG.rst
CONTRIBUTING.md
LICENSE
README.rst
pyproject.toml
biskotaki/__init__.py
biskotaki/py.typed
biskotaki-0.1.0.dist-info/LICENSE
biskotaki-0.1.0.dist-info/WHEEL
biskotaki-0.1.0.dist-info/METADATA
biskotaki-0.1.0.dist-info/RECORD
